setup.py
br_documents/__init__.py
br_documents/cpfcnpj.py
br_documents.egg-info/PKG-INFO
br_documents.egg-info/SOURCES.txt
br_documents.egg-info/dependency_links.txt
br_documents.egg-info/top_level.txt