Metadata-Version: 1.1
Name: br-documents
Version: 0.0.1
Summary: Provide objects for brazilian documents like CPF and others, with validation
Home-page: http://github.com/chronossc/br_documents
Author: Felipe 'chronos' Prenholato
Author-email: philipe.rp@gmail.com
License: UNKNOWN
Platform: UNKNOWN
Classifier: Development Status :: 4 - Beta
Classifier: Environment :: Console
Classifier: Environment :: Web Environment
Classifier: Intended Audience :: Developers
Classifier: License :: OSI Approved :: BSD License
Classifier: Operating System :: OS Independent
Classifier: Programming Language :: Python
